[
    

       

            {"Category":"Image","title":"Unsplash","logo":"../Images/Images/unsplash.png","desc":"Beautiful, free images and photos that you can download and use for any project.","link":"https://unsplash.com/"},
            {"Category":"Image","title":"Pexels","logo":"../Images/Images/pexels.png","desc":"The best free stock photos & videos shared by talented creators","link":"https://www.pexels.com/"},
            {"Category":"Image","title":"Pixabay","logo":"../Images/Images/pixabay.png","desc":"Stunning free images & royalty free stock","link":"https://pixabay.com/"},
            {"Category":"Image","title":"Stocksnap","logo":"../Images/Images/stocksnap.png","desc":"Beautiful Free Stock Photos","link":"https://stocksnap.io/"},
            {"Category":"Image","title":"Picjumbo","logo":"../Images/Images/picjumbo.png","desc":"Download free stock photos, backgrounds  for personal and commercial use","link":"https://picjumbo.com/"},
            {"Category":"Image","title":"Negativespace","logo":"../Images/Images/negativespace.png","desc":" Beautiful, High-Resolution Free Stock Photos For personal or commercial use","link":"https://negativespace.co/"},
            {"Category":"Image","title":"Burdt","logo":"../Images/Images/burst.png","desc":"A fast tool for Productivity tools and collabration","link":"https://burst.shopify.com/"},
            {"Category":"Image","title":"kaboompics","logo":"../Images/Images/kaboompics.png","desc":"A fast tool for Productivity tools and collabration","link":"https://kaboompics.com/"},
            

          
            {"Category":"Icons","title":"Illu1","logo":"../Images/tool.jpg","desc":"Lorem Ipsum is simply dummy text of the printing and typesetting industry.xsssdsdsddsdsdsdsddsd fgf gbgh fgfg","link":"https://unsplash.com/"},
            {"Category":"Icons","title":"Illu2","logo":"../Images/tool.jpg","desc":"Lorem Ipsum is simply dummy text of the printing and typesetting industry.xsssdsdsddsdsdsdsddsd fgf gbgh fgfg","link":"https://unsplash.com/"},
            {"Category":"Icons","title":"Illu2","logo":"../Images/tool.jpg","desc":"Lorem Ipsum is simply dummy text of the printing and typesetting industry.xsssdsdsddsdsdsdsddsd fgf gbgh fgfg","link":"https://unsplash.com/"},
            {"Category":"Icons","title":"Illu2","logo":"../Images/tool.jpg","desc":"Lorem Ipsum is simply dummy text of the printing and typesetting industry.xsssdsdsddsdsdsdsddsd fgf gbgh fgfg","link":"https://unsplash.com/"},

            {"Category":"Illustrations","title":"Illu1","logo":"../Images/Illustrations/tool_2.png","desc":"Lorem Ipsum is simply dummy text of the printing and typesetting industry.xsssdsdsddsdsdsdsddsd fgf gbgh fgfg","link":"https://unsplash.com/"},
            {"Category":"Illustrations","title":"Illu2","logo":"../Images/Illustrations/tool_2.png","desc":"StLorem Ipsum is simply dummy text of the printing and typesetting industry.xsssdsdsddsdsdsdsddsd fgf gbgh fgfg","link":"https://unsplash.com/"},
            {"Category":"Illustrations","title":"Illu2","logo":"../Images/Illustrations/tool_2.png","desc":"StLorem Ipsum is simply dummy text of the printing and typesetting industry.xsssdsdsddsdsdsdsddsd fgf gbgh fgfg","link":"https://unsplash.com/"},
            {"Category":"Illustrations","title":"Illu2","logo":"../Images/Illustrations/tool_2.png","desc":"StLorem Ipsum is simply dummy text of the printing and typesetting industry.xsssdsdsddsdsdsdsddsd fgf gbgh fgfg","link":"https://unsplash.com/"},
            {"Category":"Illustrations","title":"Illu2","logo":"../Images/Illustrations/tool_2.png","desc":"StLorem Ipsum is simply dummy text of the printing and typesetting industry.xsssdsdsddsdsdsdsddsd fgf gbgh fgfg","link":"https://unsplash.com/"},
            {"Category":"Illustrations","title":"Illu2","logo":"../Images/Illustrations/tool_2.png","desc":"StLorem Ipsum is simply dummy text of the printing and typesetting industry.xsssdsdsddsdsdsdsddsd fgf gbgh fgfg","link":"https://unsplash.com/"},
            {"Category":"Illustrations","title":"Illu2","logo":"../Images/Illustrations/tool_2.png","desc":"StLorem Ipsum is simply dummy text of the printing and typesetting industry.xsssdsdsddsdsdsdsddsd fgf gbgh fgfg","link":"https://unsplash.com/"},
            {"Category":"Illustrations","title":"Illu2","logo":"../Images/Illustrations/tool_2.png","desc":"StLorem Ipsum is simply dummy text of the printing and typesetting industry.xsssdsdsddsdsdsdsddsd fgf gbgh fgfg","link":"https://unsplash.com/"}
     
        
      
    
]